agentguard/__init__.py
agentguard/client.py
agentguard/lineage.py
agentguard/protect.py
agentguard_pro-0.1.4.dist-info/licenses/LICENSE
agentguard_pro-0.1.4.dist-info/METADATA
agentguard_pro-0.1.4.dist-info/WHEEL
agentguard_pro-0.1.4.dist-info/top_level.txt
agentguard_pro-0.1.4.dist-info/RECORD
